Workbook

Sheet Cover
B2: DCF & Comparable Companies Valuation
B3: Illustrative Manufacturing Co. | valuation date 31 Dec 2025 | $ thousands unless stated
B5: Purpose | C5: Values the company three ways (DCF with perpetuity growth, DCF with an exit multiple, and trading comparables) and compares them on one summary page.
B6: Data | C6: Forecast from the base case of the three-statement-model project. Market inputs and peer multiples are illustrative, not real market data.
B7: How to use | C7: Change the blue or yellow cells on the WACC, DCF and Comps sheets. Everything else is a formula.
B8: Sheets | C8: Forecast > WACC > DCF > Sensitivity > Comps > Summary
B9: Colour key | C9: Blue = hardcoded input | Black = formula | Green = link to another sheet | Yellow fill = key assumption
B10: Author | C10: Muhammed Anshaj K

Sheet Forecast
B1: Forecast inputs
B2: Illustrative Manufacturing Co. ($ thousands unless stated)
C4: 2025A | D4: 2026E | E4: 2027E | F4: 2028E | G4: 2029E | H4: 2030E
B5: Revenue | C5: 12000 | D5: 13200 | E5: 14388 | F5: 15539 | G5: 16626.8 | H5: 17624.4
B6: EBITDA | C6: 2340 | D6: 2640 | E6: 2949.5 | F6: 3340.9 | G6: 3574.8 | H6: 3877.4
B7: Depreciation & amortisation | C7: 600 | D7: 660 | E7: 719.4 | F7: 777 | G7: 831.3 | H7: 881.2
B8: EBIT | C8: =C6-C7 -> 1740 | D8: =D6-D7 -> 1980 | E8: =E6-E7 -> 2230.1 | F8: =F6-F7 -> 2563.9 | G8: =G6-G7 -> 2743.5 | H8: =H6-H7 -> 2996.2
B9: Capital expenditure | D9: 858 | E9: 863.3 | F9: 932.3 | G9: 914.5 | H9: 969.3
B10: Net working capital (AR + inventory - AP) | C10: 1940 | D10: 2133.7 | E10: 2322.8 | F10: 2505.4 | G10: 2680.8 | H10: 2841.6
B11: Net income | C11: 1155
B13: Balance sheet at 31 Dec 2025
B14: Cash | C14: 908
B15: Debt | C15: 3000
B16: Shares outstanding (thousands) | C16: 1000
B18: Source: base case of the three-statement-model project (github.com/MuhammedAnshajK/three-statement-model), rounded to 0.1. Shares outstanding are illustrative.

Sheet WACC
B1: Discount rate (WACC)
B2: Illustrative Manufacturing Co. ($ thousands unless stated)
B5: Risk-free rate | C5: 0.045 | D5: Illustrative long-term government bond yield
B6: Equity risk premium | C6: 0.055 | D6: Illustrative market premium
B7: Beta (levered) | C7: 1.1 | D7: Illustrative, in line with industrial peers
B8: Cost of equity (CAPM) | C8: =C5+C7*C6 -> 0.1055 | D8: Risk-free + beta x equity risk premium
B10: Pre-tax cost of debt | C10: 0.07 | D10: Matches the 7% interest rate in the three-statement model
B11: Tax rate | C11: 0.25 | D11: Matches the forecast tax rate
B12: After-tax cost of debt | C12: =C10*(1-C11) -> 0.0525
B14: Target debt / (debt + equity) | C14: 0.2 | D14: Illustrative target capital structure
B15: Target equity / (debt + equity) | C15: =1-C14 -> 0.8
B17: WACC | C17: =C15*C8+C14*C12 -> 0.0949 | D17: Weighted average cost of capital

Sheet DCF
B1: Discounted cash flow
B2: Illustrative Manufacturing Co. ($ thousands unless stated)
C4: 2025A | D4: 2026E | E4: 2027E | F4: 2028E | G4: 2029E | H4: 2030E
B5: EBIT | C5: =Forecast!C8 -> 1740 | D5: =Forecast!D8 -> 1980 | E5: =Forecast!E8 -> 2230.1 | F5: =Forecast!F8 -> 2563.9 | G5: =Forecast!G8 -> 2743.5 | H5: =Forecast!H8 -> 2996.2
B6: Less: tax on EBIT | D6: =-D5*WACC!$C$11 -> -495 | E6: =-E5*WACC!$C$11 -> -557.525 | F6: =-F5*WACC!$C$11 -> -640.975 | G6: =-G5*WACC!$C$11 -> -685.875 | H6: =-H5*WACC!$C$11 -> -749.05
B7: NOPAT | D7: =D5+D6 -> 1485 | E7: =E5+E6 -> 1672.575 | F7: =F5+F6 -> 1922.925 | G7: =G5+G6 -> 2057.625 | H7: =H5+H6 -> 2247.15
B8: Add: depreciation & amortisation | D8: =Forecast!D7 -> 660 | E8: =Forecast!E7 -> 719.4 | F8: =Forecast!F7 -> 777 | G8: =Forecast!G7 -> 831.3 | H8: =Forecast!H7 -> 881.2
B9: Less: capital expenditure | D9: =-Forecast!D9 -> -858 | E9: =-Forecast!E9 -> -863.3 | F9: =-Forecast!F9 -> -932.3 | G9: =-Forecast!G9 -> -914.5 | H9: =-Forecast!H9 -> -969.3
B10: Less: increase in net working capital | D10: =-(Forecast!D10-Forecast!C10) -> -193.7 | E10: =-(Forecast!E10-Forecast!D10) -> -189.1 | F10: =-(Forecast!F10-Forecast!E10) -> -182.6 | G10: =-(Forecast!G10-Forecast!F10) -> -175.4 | H10: =-(Forecast!H10-Forecast!G10) -> -160.8
B11: Unlevered free cash flow | D11: =SUM(D7:D10) -> 1093.3 | E11: =SUM(E7:E10) -> 1339.575 | F11: =SUM(F7:F10) -> 1585.025 | G11: =SUM(G7:G10) -> 1799.025 | H11: =SUM(H7:H10) -> 1998.25
B13: Discount period (years) | D13: 1 | E13: 2 | F13: 3 | G13: 4 | H13: 5
B14: Discount factor | D14: =1/(1+$C$18)^D13 -> 0.91332542 | E14: =1/(1+$C$18)^E13 -> 0.83416332 | F14: =1/(1+$C$18)^F13 -> 0.76186256 | G14: =1/(1+$C$18)^G13 -> 0.69582844 | H14: =1/(1+$C$18)^H13 -> 0.6355178
B15: Present value of free cash flow | D15: =D11*D14 -> 998.53868 | E15: =E11*E14 -> 1117.4243 | F15: =F11*F14 -> 1207.5712 | G15: =G11*G14 -> 1251.8128 | H15: =H11*H14 -> 1269.9234
B17: Assumptions
B18: WACC | C18: =WACC!C17 -> 0.0949
B19: Terminal growth rate | C19: 0.025
B20: Exit EV / EBITDA multiple | C20: 8
B22: Valuation | C22: Perpetuity | E22: Exit multiple
B23: Sum of PV of free cash flows | C23: =SUM(D15:H15) -> 5845.2704 | E23: =SUM(D15:H15) -> 5845.2704
B24: Terminal value (2030) | C24: =H11*(1+C19)/(C18-C19) -> 29301.949 | E24: =Forecast!H6*C20 -> 31019.2
B25: PV of terminal value | C25: =C24*H14 -> 18621.91 | E25: =E24*H14 -> 19713.254
B26: Enterprise value | C26: =C23+C25 -> 24467.181 | E26: =E23+E25 -> 25558.524
B27: Less: debt | C27: =-Forecast!C15 -> -3000 | E27: =-Forecast!C15 -> -3000
B28: Add: cash | C28: =Forecast!C14 -> 908 | E28: =Forecast!C14 -> 908
B29: Equity value | C29: =SUM(C26:C28) -> 22375.181 | E29: =SUM(E26:E28) -> 23466.524
B30: Value per share ($) | C30: =C29/Forecast!C16 -> 22.375181 | E30: =E29/Forecast!C16 -> 23.466524
B32: Terminal value as % of EV | C32: =C25/C26 -> 0.76109751 | E32: =E25/E26 -> 0.77129859
B33: Implied exit multiple / implied growth | C33: =C24/Forecast!H6 -> 7.5571128 | E33: =(E24*C18-H11)/(E24+H11) -> 0.028635527
B35: Cash flows are discounted at year end. Terminal value uses the 2030 free cash flow grown one year.

Sheet Sensitivity
B1: Sensitivity: value per share ($)
B2: Perpetuity growth method | WACC down the side, terminal growth across the top
B4: WACC \ growth | C4: =DCF!$C$19+(-0.01) -> 0.015 | D4: =DCF!$C$19+(-0.005) -> 0.02 | E4: =DCF!$C$19+(0) -> 0.025 | F4: =DCF!$C$19+(0.005) -> 0.03 | G4: =DCF!$C$19+(0.01) -> 0.035
B5: =DCF!$C$18+(-0.01) -> 0.0849 | C5: =(SUMPRODUCT(DCF!$D$11:$H$11/(1+$B5)^DCF!$D$13:$H$13)+DCF!$H$11*(1+C$4)/($B5-C$4)/(1+$B5)^DCF!$H$13-Forecast!$C$15+Forecast!$C$14)/Forecast!$C$16 -> 23.229186 | D5: =(SUMPRODUCT(DCF!$D$11:$H$11/(1+$B5)^DCF!$D$13:$H$13)+DCF!$H$11*(1+D$4)/($B5-D$4)/(1+$B5)^DCF!$H$13-Forecast!$C$15+Forecast!$C$14)/Forecast!$C$16 -> 24.818974 | E5: =(SUMPRODUCT(DCF!$D$11:$H$11/(1+$B5)^DCF!$D$13:$H$13)+DCF!$H$11*(1+E$4)/($B5-E$4)/(1+$B5)^DCF!$H$13-Forecast!$C$15+Forecast!$C$14)/Forecast!$C$16 -> 26.674168 | F5: =(SUMPRODUCT(DCF!$D$11:$H$11/(1+$B5)^DCF!$D$13:$H$13)+DCF!$H$11*(1+F$4)/($B5-F$4)/(1+$B5)^DCF!$H$13-Forecast!$C$15+Forecast!$C$14)/Forecast!$C$16 -> 28.867285 | G5: =(SUMPRODUCT(DCF!$D$11:$H$11/(1+$B5)^DCF!$D$13:$H$13)+DCF!$H$11*(1+G$4)/($B5-G$4)/(1+$B5)^DCF!$H$13-Forecast!$C$15+Forecast!$C$14)/Forecast!$C$16 -> 31.499905
B6: =DCF!$C$18+(-0.005) -> 0.0899 | C6: =(SUMPRODUCT(DCF!$D$11:$H$11/(1+$B6)^DCF!$D$13:$H$13)+DCF!$H$11*(1+C$4)/($B6-C$4)/(1+$B6)^DCF!$H$13-Forecast!$C$15+Forecast!$C$14)/Forecast!$C$16 -> 21.444976 | D6: =(SUMPRODUCT(DCF!$D$11:$H$11/(1+$B6)^DCF!$D$13:$H$13)+DCF!$H$11*(1+D$4)/($B6-D$4)/(1+$B6)^DCF!$H$13-Forecast!$C$15+Forecast!$C$14)/Forecast!$C$16 -> 22.797404 | E6: =(SUMPRODUCT(DCF!$D$11:$H$11/(1+$B6)^DCF!$D$13:$H$13)+DCF!$H$11*(1+E$4)/($B6-E$4)/(1+$B6)^DCF!$H$13-Forecast!$C$15+Forecast!$C$14)/Forecast!$C$16 -> 24.358219 | F6: =(SUMPRODUCT(DCF!$D$11:$H$11/(1+$B6)^DCF!$D$13:$H$13)+DCF!$H$11*(1+F$4)/($B6-F$4)/(1+$B6)^DCF!$H$13-Forecast!$C$15+Forecast!$C$14)/Forecast!$C$16 -> 26.179604 | G6: =(SUMPRODUCT(DCF!$D$11:$H$11/(1+$B6)^DCF!$D$13:$H$13)+DCF!$H$11*(1+G$4)/($B6-G$4)/(1+$B6)^DCF!$H$13-Forecast!$C$15+Forecast!$C$14)/Forecast!$C$16 -> 28.332752
B7: =DCF!$C$18+(0) -> 0.0949 | C7: =(SUMPRODUCT(DCF!$D$11:$H$11/(1+$B7)^DCF!$D$13:$H$13)+DCF!$H$11*(1+C$4)/($B7-C$4)/(1+$B7)^DCF!$H$13-Forecast!$C$15+Forecast!$C$14)/Forecast!$C$16 -> 19.88559 | D7: =(SUMPRODUCT(DCF!$D$11:$H$11/(1+$B7)^DCF!$D$13:$H$13)+DCF!$H$11*(1+D$4)/($B7-D$4)/(1+$B7)^DCF!$H$13-Forecast!$C$15+Forecast!$C$14)/Forecast!$C$16 -> 21.047288 | E7: =(SUMPRODUCT(DCF!$D$11:$H$11/(1+$B7)^DCF!$D$13:$H$13)+DCF!$H$11*(1+E$4)/($B7-E$4)/(1+$B7)^DCF!$H$13-Forecast!$C$15+Forecast!$C$14)/Forecast!$C$16 -> 22.375181 | F7: =(SUMPRODUCT(DCF!$D$11:$H$11/(1+$B7)^DCF!$D$13:$H$13)+DCF!$H$11*(1+F$4)/($B7-F$4)/(1+$B7)^DCF!$H$13-Forecast!$C$15+Forecast!$C$14)/Forecast!$C$16 -> 23.90768 | G7: =(SUMPRODUCT(DCF!$D$11:$H$11/(1+$B7)^DCF!$D$13:$H$13)+DCF!$H$11*(1+G$4)/($B7-G$4)/(1+$B7)^DCF!$H$13-Forecast!$C$15+Forecast!$C$14)/Forecast!$C$16 -> 25.696021
B8: =DCF!$C$18+(0.005) -> 0.0999 | C8: =(SUMPRODUCT(DCF!$D$11:$H$11/(1+$B8)^DCF!$D$13:$H$13)+DCF!$H$11*(1+C$4)/($B8-C$4)/(1+$B8)^DCF!$H$13-Forecast!$C$15+Forecast!$C$14)/Forecast!$C$16 -> 18.511273 | D8: =(SUMPRODUCT(DCF!$D$11:$H$11/(1+$B8)^DCF!$D$13:$H$13)+DCF!$H$11*(1+D$4)/($B8-D$4)/(1+$B8)^DCF!$H$13-Forecast!$C$15+Forecast!$C$14)/Forecast!$C$16 -> 19.517631 | E8: =(SUMPRODUCT(DCF!$D$11:$H$11/(1+$B8)^DCF!$D$13:$H$13)+DCF!$H$11*(1+E$4)/($B8-E$4)/(1+$B8)^DCF!$H$13-Forecast!$C$15+Forecast!$C$14)/Forecast!$C$16 -> 20.658349 | F8: =(SUMPRODUCT(DCF!$D$11:$H$11/(1+$B8)^DCF!$D$13:$H$13)+DCF!$H$11*(1+F$4)/($B8-F$4)/(1+$B8)^DCF!$H$13-Forecast!$C$15+Forecast!$C$14)/Forecast!$C$16 -> 21.96226 | G8: =(SUMPRODUCT(DCF!$D$11:$H$11/(1+$B8)^DCF!$D$13:$H$13)+DCF!$H$11*(1+G$4)/($B8-G$4)/(1+$B8)^DCF!$H$13-Forecast!$C$15+Forecast!$C$14)/Forecast!$C$16 -> 23.467083
B9: =DCF!$C$18+(0.01) -> 0.1049 | C9: =(SUMPRODUCT(DCF!$D$11:$H$11/(1+$B9)^DCF!$D$13:$H$13)+DCF!$H$11*(1+C$4)/($B9-C$4)/(1+$B9)^DCF!$H$13-Forecast!$C$15+Forecast!$C$14)/Forecast!$C$16 -> 17.291116 | D9: =(SUMPRODUCT(DCF!$D$11:$H$11/(1+$B9)^DCF!$D$13:$H$13)+DCF!$H$11*(1+D$4)/($B9-D$4)/(1+$B9)^DCF!$H$13-Forecast!$C$15+Forecast!$C$14)/Forecast!$C$16 -> 18.169452 | E9: =(SUMPRODUCT(DCF!$D$11:$H$11/(1+$B9)^DCF!$D$13:$H$13)+DCF!$H$11*(1+E$4)/($B9-E$4)/(1+$B9)^DCF!$H$13-Forecast!$C$15+Forecast!$C$14)/Forecast!$C$16 -> 19.157717 | F9: =(SUMPRODUCT(DCF!$D$11:$H$11/(1+$B9)^DCF!$D$13:$H$13)+DCF!$H$11*(1+F$4)/($B9-F$4)/(1+$B9)^DCF!$H$13-Forecast!$C$15+Forecast!$C$14)/Forecast!$C$16 -> 20.277927 | G9: =(SUMPRODUCT(DCF!$D$11:$H$11/(1+$B9)^DCF!$D$13:$H$13)+DCF!$H$11*(1+G$4)/($B9-G$4)/(1+$B9)^DCF!$H$13-Forecast!$C$15+Forecast!$C$14)/Forecast!$C$16 -> 21.558395
B11: Centre cell (yellow) equals the base case on the DCF sheet.
B12: Check: centre less DCF value per share | E12: =ROUND(E7-DCF!C30,6) -> 0

Sheet Comps
B1: Trading comparables
B2: Illustrative peer group | multiples are made up for this example
C4: EV / Revenue | D4: EV / EBITDA | E4: P / E
B5: Peer A (industrial machinery) | C5: 1.4 | D5: 8.5 | E5: 14.2
B6: Peer B (components) | C6: 1.1 | D6: 7.2 | E6: 12.5
B7: Peer C (automation) | C7: 1.9 | D7: 9.8 | E7: 17
B8: Peer D (metal products) | C8: 1 | D8: 6.9 | E8: 11.8
B9: Peer E (equipment) | C9: 1.3 | D9: 8.1 | E9: 13.9
B10: Peer F (precision parts) | C10: 2.1 | D10: 10.4 | E10: 18.5
B12: 25th percentile | C12: =QUARTILE(C5:C10,1) -> 1.15 | D12: =QUARTILE(D5:D10,1) -> 7.425 | E12: =QUARTILE(E5:E10,1) -> 12.85
B13: Median | C13: =MEDIAN(C5:C10) -> 1.35 | D13: =MEDIAN(D5:D10) -> 8.3 | E13: =MEDIAN(E5:E10) -> 14.05
B14: 75th percentile | C14: =QUARTILE(C5:C10,3) -> 1.775 | D14: =QUARTILE(D5:D10,3) -> 9.475 | E14: =QUARTILE(E5:E10,3) -> 16.3
B16: Company metric (2025A) | C16: =Forecast!C5 -> 12000 | D16: =Forecast!C6 -> 2340 | E16: =Forecast!C11 -> 1155
B18: Implied value per share ($)
B19: At 25th percentile | C19: =(C12*C$16-Forecast!$C$15+Forecast!$C$14)/Forecast!$C$16 -> 11.708 | D19: =(D12*D$16-Forecast!$C$15+Forecast!$C$14)/Forecast!$C$16 -> 15.2825 | E19: =E12*E$16/Forecast!$C$16 -> 14.84175
B20: At median | C20: =(C13*C$16-Forecast!$C$15+Forecast!$C$14)/Forecast!$C$16 -> 14.108 | D20: =(D13*D$16-Forecast!$C$15+Forecast!$C$14)/Forecast!$C$16 -> 17.33 | E20: =E13*E$16/Forecast!$C$16 -> 16.22775
B21: At 75th percentile | C21: =(C14*C$16-Forecast!$C$15+Forecast!$C$14)/Forecast!$C$16 -> 19.208 | D21: =(D14*D$16-Forecast!$C$15+Forecast!$C$14)/Forecast!$C$16 -> 20.0795 | E21: =E14*E$16/Forecast!$C$16 -> 18.8265

Sheet Summary
B1: Valuation summary
B2: Value per share ($) | the bars in the chart run from low to high
C4: Low | D4: High | E4: Range | F4: Base
B5: DCF: perpetuity growth (sensitivity) | C5: =MIN(Sensitivity!C5:G9) -> 17.291116 | D5: =MAX(Sensitivity!C5:G9) -> 31.499905 | E5: =D5-C5 -> 14.208789 | F5: =DCF!C30 -> 22.375181
B6: DCF: exit multiple (7.0x to 9.0x) | C6: =(DCF!C23+(DCF!C20-1)*Forecast!H6*DCF!H14-Forecast!C15+Forecast!C14)/Forecast!C16 -> 21.002368 | D6: =(DCF!C23+(DCF!C20+1)*Forecast!H6*DCF!H14-Forecast!C15+Forecast!C14)/Forecast!C16 -> 25.930681 | E6: =D6-C6 -> 4.9283135 | F6: =DCF!E30 -> 23.466524
B7: Comps: EV / EBITDA (25th to 75th pct) | C7: =Comps!D19 -> 15.2825 | D7: =Comps!D21 -> 20.0795 | E7: =D7-C7 -> 4.797 | F7: =Comps!D20 -> 17.33
B8: Comps: EV / Revenue (25th to 75th pct) | C8: =Comps!C19 -> 11.708 | D8: =Comps!C21 -> 19.208 | E8: =D8-C8 -> 7.5 | F8: =Comps!C20 -> 14.108
B9: Comps: P / E (25th to 75th pct) | C9: =Comps!E19 -> 14.84175 | D9: =Comps!E21 -> 18.8265 | E9: =D9-C9 -> 3.98475 | F9: =Comps!E20 -> 16.22775
B11: Midpoint of all ranges | C11: =AVERAGE(C5:C9) -> 16.025147 | D11: =AVERAGE(D5:D9) -> 23.108917 | F11: =(C11+D11)/2 -> 19.567032
B13: The DCF sits above the trading comps because the forecast assumes margins expand from 19.5% to 22.0% EBITDA. Peers are valued on today's earnings.
