Workbook

Sheet Cover
B2: NIKE, Inc.: DCF & Comparable Companies Valuation
B3: Valuation date 19 Oct 2026 | share price $37.21 | $ millions unless stated
B5: Purpose | C5: Values Nike three ways (DCF with perpetuity growth, DCF with an exit multiple, and trading comparables) and compares them with the share price on one football field chart.
B6: Data | C6: Cash flows from the base case of the Nike five-year forecast (github.com/MuhammedAnshajK/three-statement-model), whose FY2027 matches Nike's guidance of 1 Oct 2026. Share price, beta and peer multiples from stockanalysis.com at 19 Oct 2026; 10-year Treasury yield from YCharts (16 Oct 2026). Net debt from the 31 May 2026 balance sheet (10-K).
B7: How to use | C7: Change the blue or yellow cells on the WACC, DCF and Comps sheets. Everything else is a formula.
B8: Sheets | C8: Summary > Forecast > WACC > DCF > Sensitivity > Comps
B9: Colour key | C9: Blue = hardcoded input | Black = formula | Green = link to another sheet | Yellow fill = key assumption
B10: Note | C10: A learning project, not investment advice.
B11: Author | C11: Muhammed Anshaj K

Sheet Summary
B1: Valuation summary
B2: Value per share ($) | the bars in the chart run from low to high
C4: Low | D4: High | E4: Range | F4: Base
B5: DCF: perpetuity growth (sensitivity) | C5: =MIN(Sensitivity!C5:G9) -> 29.751551 | D5: =MAX(Sensitivity!C5:G9) -> 51.182386 | E5: =D5-C5 -> 21.430835 | F5: =DCF!C30 -> 37.358781
B6: DCF: exit multiple (9.0x to 11.0x) | C6: =(DCF!C23+(DCF!C20-1)*Forecast!H6*DCF!H14-Forecast!C15+Forecast!C14)/Forecast!C16 -> 33.907042 | D6: =(DCF!C23+(DCF!C20+1)*Forecast!H6*DCF!H14-Forecast!C15+Forecast!C14)/Forecast!C16 -> 39.354418 | E6: =D6-C6 -> 5.447376 | F6: =DCF!E30 -> 36.63073
B7: Comps: EV / EBITDA (25th to 75th pct) | C7: =Comps!D19 -> 27.502155 | D7: =Comps!D21 -> 58.159327 | E7: =D7-C7 -> 30.657172 | F7: =Comps!D20 -> 32.902559
B8: Comps: EV / Revenue (25th to 75th pct) | C8: =Comps!C19 -> 27.074899 | D8: =Comps!C21 -> 55.505067 | E8: =D8-C8 -> 28.430168 | F8: =Comps!C20 -> 35.959327
B9: Comps: forward P / E (25th to 75th pct) | C9: =Comps!E19 -> 14.56875 | D9: =Comps!E21 -> 20.203125 | E9: =D9-C9 -> 5.634375 | F9: =Comps!E20 -> 16.8375
B10: 52-week trading range | C10: =Forecast!C19 -> 31.97 | D10: =Forecast!D19 -> 70.44 | E10: =D10-C10 -> 38.47 | F10: =Forecast!C17 -> 37.21
B12: Current share price (19 Oct 2026) | F12: =Forecast!C17 -> 37.21
B13: DCF midpoint (perpetuity and exit multiple) | F13: =AVERAGE(F5:F6) -> 36.994755
B14: Upside / (downside) to share price | F14: =F13/F12-1 -> -0.0057845899
B16: Base column: DCF base cases, comps at the median, and the current price for the trading range.
B17: Forward P/E gives a low value because FY2027 earnings are temporarily depressed; the DCF captures the recovery.

Sheet Forecast
B1: Forecast inputs
B2: NIKE, Inc. | $ millions unless stated | market data at 19 Oct 2026
C4: FY2026A | D4: FY2027E | E4: FY2028E | F4: FY2029E | G4: FY2030E | H4: FY2031E
B5: Revenue | C5: 46398 | D5: 42441.5 | E5: 43237.1 | F5: 45140.2 | G5: 47196.8 | H5: 49130
B6: EBITDA | C6: 4544 | D6: 2673.9 | E6: 3631.9 | F6: 4604.3 | G6: 5474.8 | H6: 6239.5
B7: Depreciation & amortisation | C7: 747 | D7: 679.1 | E7: 691.8 | F7: 722.2 | G7: 755.1 | H7: 786.1
B8: EBIT | C8: =C6-C7 -> 3797 | D8: =D6-D7 -> 1994.8 | E8: =E6-E7 -> 2940.1 | F8: =F6-F7 -> 3882.1 | G8: =G6-G7 -> 4719.7 | H8: =H6-H7 -> 5453.4
B9: Capital expenditure | C9: 684 | D9: 679.1 | E9: 691.8 | F9: 722.2 | G9: 755.1 | H9: 786.1
B10: Operating working capital (AR + inventory + prepaid - AP - accrued) | C10: 5884 | D10: 4851.7 | E10: 4541 | F10: 4324.3 | G10: 4419.1 | H10: 4569.8
B11: Diluted EPS ($) | C11: 2.1 | D11: 1.09 | E11: 1.63 | F11: 2.19 | G11: 2.73 | H11: 3.23
B13: Balance sheet at 31 May 2026 and market data
B14: Cash and short-term investments | C14: 9027
B15: Debt (excluding leases) | C15: 7942
B16: Shares outstanding (m) | C16: 1485
B17: Share price at 19 Oct 2026 ($) | C17: 37.21
B18: Market capitalisation | C18: =C16*C17 -> 55256.85
B19: 52-week low / high ($) | C19: 31.97 | D19: 70.44
B21: Revenue, EBITDA, D&A, capex, working capital and EPS: base case of the Nike forecast model (rounded to 0.1). FY2026A EPS is reported diluted EPS.
B22: Shares: market cap $55.27bn / $37.21 (stockanalysis.com). Debt and cash: Nike 10-K, 31 May 2026.

Sheet WACC
B1: Discount rate (WACC)
B2: NIKE, Inc. | $ millions unless stated | market data at 19 Oct 2026
B5: Risk-free rate | C5: 0.0509 | D5: US 10-year Treasury yield, 16 Oct 2026 (YCharts)
B6: Equity risk premium | C6: 0.05 | D6: Assumption, within the common 4% to 6% range
B7: Beta (levered) | C7: 1.1 | D7: Nike 5-year beta (stockanalysis.com)
B8: Cost of equity (CAPM) | C8: =C5+C7*C6 -> 0.1059 | D8: Risk-free + beta x equity risk premium
B10: Pre-tax cost of debt | C10: 0.059 | D10: Risk-free rate plus about 0.8% for an A-rated issuer
B11: Tax rate | C11: 0.19 | D11: Matches the forecast tax rate
B12: After-tax cost of debt | C12: =C10*(1-C11) -> 0.04779
B14: Debt / (debt + equity) | C14: =Forecast!C15/(Forecast!C15+Forecast!C18) -> 0.12566684 | D14: Market-value weights: debt $7.9bn, market cap $55.3bn
B15: Equity / (debt + equity) | C15: =1-C14 -> 0.87433316
B17: WACC | C17: =C15*C8+C14*C12 -> 0.0985975 | D17: Weighted average cost of capital

Sheet DCF
B1: Discounted cash flow
B2: NIKE, Inc. | $ millions unless stated | market data at 19 Oct 2026
C4: FY2026A | D4: FY2027E | E4: FY2028E | F4: FY2029E | G4: FY2030E | H4: FY2031E
B5: EBIT | C5: =Forecast!C8 -> 3797 | D5: =Forecast!D8 -> 1994.8 | E5: =Forecast!E8 -> 2940.1 | F5: =Forecast!F8 -> 3882.1 | G5: =Forecast!G8 -> 4719.7 | H5: =Forecast!H8 -> 5453.4
B6: Less: tax on EBIT | D6: =-D5*WACC!$C$11 -> -379.012 | E6: =-E5*WACC!$C$11 -> -558.619 | F6: =-F5*WACC!$C$11 -> -737.599 | G6: =-G5*WACC!$C$11 -> -896.743 | H6: =-H5*WACC!$C$11 -> -1036.146
B7: NOPAT | D7: =D5+D6 -> 1615.788 | E7: =E5+E6 -> 2381.481 | F7: =F5+F6 -> 3144.501 | G7: =G5+G6 -> 3822.957 | H7: =H5+H6 -> 4417.254
B8: Add: depreciation & amortisation | D8: =Forecast!D7 -> 679.1 | E8: =Forecast!E7 -> 691.8 | F8: =Forecast!F7 -> 722.2 | G8: =Forecast!G7 -> 755.1 | H8: =Forecast!H7 -> 786.1
B9: Less: capital expenditure | D9: =-Forecast!D9 -> -679.1 | E9: =-Forecast!E9 -> -691.8 | F9: =-Forecast!F9 -> -722.2 | G9: =-Forecast!G9 -> -755.1 | H9: =-Forecast!H9 -> -786.1
B10: Less: increase in working capital | D10: =-(Forecast!D10-Forecast!C10) -> 1032.3 | E10: =-(Forecast!E10-Forecast!D10) -> 310.7 | F10: =-(Forecast!F10-Forecast!E10) -> 216.7 | G10: =-(Forecast!G10-Forecast!F10) -> -94.8 | H10: =-(Forecast!H10-Forecast!G10) -> -150.7
B11: Unlevered free cash flow | D11: =SUM(D7:D10) -> 2648.088 | E11: =SUM(E7:E10) -> 2692.181 | F11: =SUM(F7:F10) -> 3361.201 | G11: =SUM(G7:G10) -> 3728.157 | H11: =SUM(H7:H10) -> 4266.554
B13: Discount period (years) | D13: 0.61 | E13: 1.61 | F13: 2.61 | G13: 3.61 | H13: 4.61
B14: Discount factor | D14: =1/(1+$C$18)^D13 -> 0.94425317 | E14: =1/(1+$C$18)^E13 -> 0.85950784 | F14: =1/(1+$C$18)^F13 -> 0.78236829 | G14: =1/(1+$C$18)^G13 -> 0.71215189 | H14: =1/(1+$C$18)^H13 -> 0.64823731
B15: Present value of free cash flow | D15: =D11*D14 -> 2500.4655 | E15: =E11*E14 -> 2313.9507 | F15: =F11*F14 -> 2629.6971 | G15: =G11*G14 -> 2655.0141 | H15: =H11*H14 -> 2765.7395
B17: Assumptions
B18: WACC | C18: =WACC!C17 -> 0.0985975
B19: Terminal growth rate | C19: 0.03
B20: Exit EV / EBITDA multiple | C20: 10
B22: Valuation | C22: Perpetuity | E22: Exit multiple
B23: Sum of PV of free cash flows | C23: =SUM(D15:H15) -> 12864.867 | E23: =SUM(D15:H15) -> 12864.867
B24: Terminal value (FY2031) | C24: =H11*(1+C19)/(C18-C19) -> 64062.84 | E24: =Forecast!H6*C20 -> 62395
B25: PV of terminal value | C25: =C24*H14 -> 41527.923 | E25: =E24*H14 -> 40446.767
B26: Enterprise value | C26: =C23+C25 -> 54392.79 | E26: =E23+E25 -> 53311.634
B27: Less: debt | C27: =-Forecast!C15 -> -7942 | E27: =-Forecast!C15 -> -7942
B28: Add: cash | C28: =Forecast!C14 -> 9027 | E28: =Forecast!C14 -> 9027
B29: Equity value | C29: =SUM(C26:C28) -> 55477.79 | E29: =SUM(E26:E28) -> 54396.634
B30: Value per share ($) | C30: =C29/Forecast!C16 -> 37.358781 | E30: =E29/Forecast!C16 -> 36.63073
B31: Upside / (downside) to share price | C31: =C30/Forecast!C17-1 -> 0.003998413 | E31: =E30/Forecast!C17-1 -> -0.015567593
B32: Terminal value as % of EV | C32: =C25/C26 -> 0.76348213 | E32: =E25/E26 -> 0.75868557
B33: Implied exit multiple / implied growth | C33: =C24/Forecast!H6 -> 10.267303 | E33: =(E24*C18-H11)/(E24+H11) -> 0.028283724
B35: Cash flows are discounted to 19 Oct 2026 at each 31 May year end (0.61 years to the FY2027 year end).
B36: FY2027 is counted in full, a small simplification. Share-based pay is treated as a real cost (not added back).
B37: Terminal value uses FY2031 free cash flow grown one year.

Sheet Sensitivity
B1: Sensitivity: value per share ($)
B2: Perpetuity growth method | WACC down the side, terminal growth across the top | share price $37.21
B4: WACC \ growth | C4: =DCF!$C$19+(-0.01) -> 0.02 | D4: =DCF!$C$19+(-0.005) -> 0.025 | E4: =DCF!$C$19+(0) -> 0.03 | F4: =DCF!$C$19+(0.005) -> 0.035 | G4: =DCF!$C$19+(0.01) -> 0.04
B5: =DCF!$C$18+(-0.01) -> 0.0885975 | C5: =(SUMPRODUCT(DCF!$D$11:$H$11/(1+$B5)^DCF!$D$13:$H$13)+DCF!$H$11*(1+C$4)/($B5-C$4)/(1+$B5)^DCF!$H$13-Forecast!$C$15+Forecast!$C$14)/Forecast!$C$16 -> 38.495135 | D5: =(SUMPRODUCT(DCF!$D$11:$H$11/(1+$B5)^DCF!$D$13:$H$13)+DCF!$H$11*(1+D$4)/($B5-D$4)/(1+$B5)^DCF!$H$13-Forecast!$C$15+Forecast!$C$14)/Forecast!$C$16 -> 40.918849 | E5: =(SUMPRODUCT(DCF!$D$11:$H$11/(1+$B5)^DCF!$D$13:$H$13)+DCF!$H$11*(1+E$4)/($B5-E$4)/(1+$B5)^DCF!$H$13-Forecast!$C$15+Forecast!$C$14)/Forecast!$C$16 -> 43.756184 | F5: =(SUMPRODUCT(DCF!$D$11:$H$11/(1+$B5)^DCF!$D$13:$H$13)+DCF!$H$11*(1+F$4)/($B5-F$4)/(1+$B5)^DCF!$H$13-Forecast!$C$15+Forecast!$C$14)/Forecast!$C$16 -> 47.122897 | G5: =(SUMPRODUCT(DCF!$D$11:$H$11/(1+$B5)^DCF!$D$13:$H$13)+DCF!$H$11*(1+G$4)/($B5-G$4)/(1+$B5)^DCF!$H$13-Forecast!$C$15+Forecast!$C$14)/Forecast!$C$16 -> 51.182386
B6: =DCF!$C$18+(-0.005) -> 0.0935975 | C6: =(SUMPRODUCT(DCF!$D$11:$H$11/(1+$B6)^DCF!$D$13:$H$13)+DCF!$H$11*(1+C$4)/($B6-C$4)/(1+$B6)^DCF!$H$13-Forecast!$C$15+Forecast!$C$14)/Forecast!$C$16 -> 35.861073 | D6: =(SUMPRODUCT(DCF!$D$11:$H$11/(1+$B6)^DCF!$D$13:$H$13)+DCF!$H$11*(1+D$4)/($B6-D$4)/(1+$B6)^DCF!$H$13-Forecast!$C$15+Forecast!$C$14)/Forecast!$C$16 -> 37.921104 | E6: =(SUMPRODUCT(DCF!$D$11:$H$11/(1+$B6)^DCF!$D$13:$H$13)+DCF!$H$11*(1+E$4)/($B6-E$4)/(1+$B6)^DCF!$H$13-Forecast!$C$15+Forecast!$C$14)/Forecast!$C$16 -> 40.305053 | F6: =(SUMPRODUCT(DCF!$D$11:$H$11/(1+$B6)^DCF!$D$13:$H$13)+DCF!$H$11*(1+F$4)/($B6-F$4)/(1+$B6)^DCF!$H$13-Forecast!$C$15+Forecast!$C$14)/Forecast!$C$16 -> 43.095836 | G6: =(SUMPRODUCT(DCF!$D$11:$H$11/(1+$B6)^DCF!$D$13:$H$13)+DCF!$H$11*(1+G$4)/($B6-G$4)/(1+$B6)^DCF!$H$13-Forecast!$C$15+Forecast!$C$14)/Forecast!$C$16 -> 46.407312
B7: =DCF!$C$18+(0) -> 0.0985975 | C7: =(SUMPRODUCT(DCF!$D$11:$H$11/(1+$B7)^DCF!$D$13:$H$13)+DCF!$H$11*(1+C$4)/($B7-C$4)/(1+$B7)^DCF!$H$13-Forecast!$C$15+Forecast!$C$14)/Forecast!$C$16 -> 33.563828 | D7: =(SUMPRODUCT(DCF!$D$11:$H$11/(1+$B7)^DCF!$D$13:$H$13)+DCF!$H$11*(1+D$4)/($B7-D$4)/(1+$B7)^DCF!$H$13-Forecast!$C$15+Forecast!$C$14)/Forecast!$C$16 -> 35.332395 | E7: =(SUMPRODUCT(DCF!$D$11:$H$11/(1+$B7)^DCF!$D$13:$H$13)+DCF!$H$11*(1+E$4)/($B7-E$4)/(1+$B7)^DCF!$H$13-Forecast!$C$15+Forecast!$C$14)/Forecast!$C$16 -> 37.358781 | F7: =(SUMPRODUCT(DCF!$D$11:$H$11/(1+$B7)^DCF!$D$13:$H$13)+DCF!$H$11*(1+F$4)/($B7-F$4)/(1+$B7)^DCF!$H$13-Forecast!$C$15+Forecast!$C$14)/Forecast!$C$16 -> 39.703793 | G7: =(SUMPRODUCT(DCF!$D$11:$H$11/(1+$B7)^DCF!$D$13:$H$13)+DCF!$H$11*(1+G$4)/($B7-G$4)/(1+$B7)^DCF!$H$13-Forecast!$C$15+Forecast!$C$14)/Forecast!$C$16 -> 42.448995
B8: =DCF!$C$18+(0.005) -> 0.1035975 | C8: =(SUMPRODUCT(DCF!$D$11:$H$11/(1+$B8)^DCF!$D$13:$H$13)+DCF!$H$11*(1+C$4)/($B8-C$4)/(1+$B8)^DCF!$H$13-Forecast!$C$15+Forecast!$C$14)/Forecast!$C$16 -> 31.542927 | D8: =(SUMPRODUCT(DCF!$D$11:$H$11/(1+$B8)^DCF!$D$13:$H$13)+DCF!$H$11*(1+D$4)/($B8-D$4)/(1+$B8)^DCF!$H$13-Forecast!$C$15+Forecast!$C$14)/Forecast!$C$16 -> 33.074622 | E8: =(SUMPRODUCT(DCF!$D$11:$H$11/(1+$B8)^DCF!$D$13:$H$13)+DCF!$H$11*(1+E$4)/($B8-E$4)/(1+$B8)^DCF!$H$13-Forecast!$C$15+Forecast!$C$14)/Forecast!$C$16 -> 34.814434 | F8: =(SUMPRODUCT(DCF!$D$11:$H$11/(1+$B8)^DCF!$D$13:$H$13)+DCF!$H$11*(1+F$4)/($B8-F$4)/(1+$B8)^DCF!$H$13-Forecast!$C$15+Forecast!$C$14)/Forecast!$C$16 -> 36.807872 | G8: =(SUMPRODUCT(DCF!$D$11:$H$11/(1+$B8)^DCF!$D$13:$H$13)+DCF!$H$11*(1+G$4)/($B8-G$4)/(1+$B8)^DCF!$H$13-Forecast!$C$15+Forecast!$C$14)/Forecast!$C$16 -> 39.114756
B9: =DCF!$C$18+(0.01) -> 0.1085975 | C9: =(SUMPRODUCT(DCF!$D$11:$H$11/(1+$B9)^DCF!$D$13:$H$13)+DCF!$H$11*(1+C$4)/($B9-C$4)/(1+$B9)^DCF!$H$13-Forecast!$C$15+Forecast!$C$14)/Forecast!$C$16 -> 29.751551 | D9: =(SUMPRODUCT(DCF!$D$11:$H$11/(1+$B9)^DCF!$D$13:$H$13)+DCF!$H$11*(1+D$4)/($B9-D$4)/(1+$B9)^DCF!$H$13-Forecast!$C$15+Forecast!$C$14)/Forecast!$C$16 -> 31.088369 | E9: =(SUMPRODUCT(DCF!$D$11:$H$11/(1+$B9)^DCF!$D$13:$H$13)+DCF!$H$11*(1+E$4)/($B9-E$4)/(1+$B9)^DCF!$H$13-Forecast!$C$15+Forecast!$C$14)/Forecast!$C$16 -> 32.595271 | F9: =(SUMPRODUCT(DCF!$D$11:$H$11/(1+$B9)^DCF!$D$13:$H$13)+DCF!$H$11*(1+F$4)/($B9-F$4)/(1+$B9)^DCF!$H$13-Forecast!$C$15+Forecast!$C$14)/Forecast!$C$16 -> 34.306922 | G9: =(SUMPRODUCT(DCF!$D$11:$H$11/(1+$B9)^DCF!$D$13:$H$13)+DCF!$H$11*(1+G$4)/($B9-G$4)/(1+$B9)^DCF!$H$13-Forecast!$C$15+Forecast!$C$14)/Forecast!$C$16 -> 36.268094
B11: Centre cell (yellow) equals the base case on the DCF sheet.
B12: Check: centre less DCF value per share | E12: =ROUND(E7-DCF!C30,6) -> 0

Sheet Comps
B1: Trading comparables
B2: Athletic footwear and apparel peers | stockanalysis.com, 19 Oct 2026 (Puma 7 Oct) | n.m. = not meaningful
C4: EV / Revenue | D4: EV / EBITDA | E4: Forward P / E
B5: adidas (Germany) | C5: 1.24 | D5: 9.77 | E5: 15.21
B6: Puma (Germany) | C6: 0.79 | D6: n.m. | E6: n.m.
B7: Lululemon (US) | C7: 1.04 | D7: 4.86 | E7: 11.73
B8: Deckers Outdoor (US) | C8: 1.95 | D8: 8.13 | E8: 11.43
B9: On Holding (Switzerland) | C9: 2.78 | D9: 18.25 | E9: 19.02
B10: Under Armour (US) | C10: 0.61 | D10: 17.44 | E10: n.m.
B12: 25th percentile | C12: =QUARTILE(C5:C10,1) -> 0.8525 | D12: =QUARTILE(D5:D10,1) -> 8.13 | E12: =QUARTILE(E5:E10,1) -> 11.655
B13: Median | C13: =MEDIAN(C5:C10) -> 1.14 | D13: =MEDIAN(D5:D10) -> 9.77 | E13: =MEDIAN(E5:E10) -> 13.47
B14: 75th percentile | C14: =QUARTILE(C5:C10,3) -> 1.7725 | D14: =QUARTILE(D5:D10,3) -> 17.44 | E14: =QUARTILE(E5:E10,3) -> 16.1625
B15: Nike today (for reference) | C15: 1.26 | D15: 11.86 | E15: 28.41
B16: Nike metric | C16: 45890 | D16: 4890 | E16: 1.25
B17: Revenue and EBITDA: last twelve months to Aug 2026 (stockanalysis.com). EPS: midpoint of FY2027 guidance ($1.15 to $1.35, adjusted).
B18: Implied value per share ($)
B19: At 25th percentile | C19: =(C12*C$16-Forecast!$C$15+Forecast!$C$14)/Forecast!$C$16 -> 27.074899 | D19: =(D12*D$16-Forecast!$C$15+Forecast!$C$14)/Forecast!$C$16 -> 27.502155 | E19: =E12*E$16 -> 14.56875
B20: At median | C20: =(C13*C$16-Forecast!$C$15+Forecast!$C$14)/Forecast!$C$16 -> 35.959327 | D20: =(D13*D$16-Forecast!$C$15+Forecast!$C$14)/Forecast!$C$16 -> 32.902559 | E20: =E13*E$16 -> 16.8375
B21: At 75th percentile | C21: =(C14*C$16-Forecast!$C$15+Forecast!$C$14)/Forecast!$C$16 -> 55.505067 | D21: =(D14*D$16-Forecast!$C$15+Forecast!$C$14)/Forecast!$C$16 -> 58.159327 | E21: =E14*E$16 -> 20.203125
B23: Puma's EBITDA is negative and its earnings and Under Armour's are loss-making or near zero, so those multiples are excluded (n.m.).
